setup.py
validator_sahala/__init__.py
validator_sahala/validator_sahala.py
validator_sahala.egg-info/PKG-INFO
validator_sahala.egg-info/SOURCES.txt
validator_sahala.egg-info/dependency_links.txt
validator_sahala.egg-info/requires.txt
validator_sahala.egg-info/top_level.txt