Metadata-Version: 1.0
Name: validator-sahala
Version: 1.2.1
Summary: An feature extraction algorithm
Home-page: https://github.com/
Author: liyubin
Author-email: 1399393088@qq.com
License: MIT Licence
Keywords: pip,validator_sahala,featureextraction
Platform: any
